{"32":["$","$","$","$","$"],"33":["||","L|","  ","()","  "],"34":["    ","[][]","  $ ","  $ ","    "],"35":["       ","_||_||_"," || || ","-L|-L|-","       "],"36":[" |L ","/ _|","\\_ \\","|__/"," L| "],"37":["    ","()/7"," // ","//()","    "],"38":[" _  ","(o) ","/oV7","\\_n\\","    "],"39":[" _","//"," $"," $","  "],"40":["  _"," //","||$","||$"," \\\\"],"41":["_  ","\\\\ ","$||","$||","// "],"42":[". ,"," x ","' `"," $ ","   "],"43":["      "," _||_ ","|_  _|","  L|  ","      "],"44":["   ","   ","   ","()$","V  "],"45":["    ","    "," __ ","|__|","    "],"46":["   ","   ","   ","()$","   "],"47":["   _","  //"," // ","//  ","    "],"48":["  _  "," / \\ ","| 0 |"," \\_/ ","     "],"49":[" _ ","/o|","$||","$L|","   "],"50":[" __ ","[o )"," /( ","/__|","    "],"51":[" ___","|_ /","__)\\","\\__/","    "],"52":["   . ","  /| "," /o| ","L___|","     "],"53":[" __ ","| _/","\\_ \\","|__/","    "],"54":["  _ "," // ","/o \\","\\__/","    "],"55":[" ____","|__ /","  // "," //  ","     "],"56":[" __ ","(o )","/o \\","\\__/","    "],"57":[" __ ","/o \\","\\_ /"," // ","    "],"58":["  ","  ","()","()","  "],"59":["  ","  ","()","()","V "],"60":["  _"," //","<<$"," \\\\","   "],"61":["     "," ___ ","|___|","|___|","     "],"62":["_  ","\\\\ ","$>>","// ","   "],"63":[" __ ","|o )"," // "," $  "," () "],"64":["  __ "," /_ \\","((o_/","$\\__7","     "],"65":["  _  "," / \\ ","| o |","|_n_|","     "],"66":[" ___ ","| o )","| o \\","|___/","     "],"67":["  __ "," / _|","( (_ "," \\__|","     "],"68":[" __  ","|  \\ ","| o )","|__/ ","     "],"69":[" ___ ","| __|","| _| ","|___|","     "],"70":[" ___ ","| __|","| _| ","|_|  ","     "],"71":["  __ "," / _|","( |_n"," \\__/","     "],"72":[" _ _ ","| U |","|   |","|_n_|","     "],"73":[" _ ","| |","| |","|_|","   "],"74":["   _ ","  | |","n_| |","\\__/ ","     "],"75":[" _  _","| |//","|  ( ","|_|\\\\","     "],"76":[" _   ","| |  ","| |_ ","|___|","     "],"77":[" _   _ ","| \\_/ |","| \\_/ |","|_| |_|","       "],"78":[" _  _ ","| \\| |","| \\\\ |","|_|\\_|","      "],"79":["  _  "," / \\ ","( o )"," \\_/ ","     "],"80":[" ___ ","| o \\","|  _/","|_|  ","     "],"81":["  _  "," / \\ ","( o )"," \\_,7","     "],"82":[" ___ ","| o \\","|   /","|_|\\\\","     "],"83":[" __ ","/ _|","\\_ \\","|__/","    "],"84":[" ___ ","|_ _|"," | | "," |_| ","     "],"85":[" _ _ ","| | |","| U |","|___|","     "],"86":[" _ _ ","| | |","| V |"," \\_/ ","     "],"87":[" _ _ _ ","| | | |","| V V |"," \\_n_/ ","       "],"88":["__ __","\\ V /"," ) ( ","/_n_\\","     "],"89":["__ __","\\ V /"," \\ / "," |_| ","     "],"90":[" ___ ","|_ / "," /(_ ","/___|","     "],"91":[" __ ","| _|","| |$","| |$","|__|"],"92":["_   ","\\\\  "," \\\\ ","  \\\\","    "],"93":[" __ ","|_ |","$| |","$| |","|__|"],"94":[" _ ","/n\\"," $ "," $ ","   "],"95":["     ","     ","     "," ___ ","|___|"],"96":["_ ","\\\\"," $"," $","  "],"97":["    "," _  ","/o\\ ","\\_,]","    "],"98":["   ","|| ","|o\\","|_/","   "],"99":["  "," _","//","\\\\","  "],"100":["   "," ||","/o|","\\_|","   "],"101":["   "," _ ","/o\\","\\( ","   "],"102":[" __ ","/ _|","| ] ","L|  ","    "],"103":["   "," _ ","/o\\","\\_/"," _)"],"104":["   ","|| ","| \\","Ln|","   "],"105":["  ","()","||","L|","  "],"106":["  ","()","||","||","//"],"107":["   ","|| ","|/7","L|\\","   "],"108":["  ","||","||","L|","  "],"109":["      ","  _ _ ","|/ \\ \\","L_n_n|","      "],"110":["    ","  _ ","|/ \\","L_n|","    "],"111":["   "," _ ","/o\\","\\_/","   "],"112":["   "," _ ","/o\\","|_/","L| "],"113":["   "," _ ","/o\\","\\_|"," L|"],"114":["   "," _ ","/_|","L|$","   "],"115":["   "," _ ","(c'","\\_)","   "],"116":["   ","|| ","| ]","L| ","   "],"117":["   ","   ","|U|","\\_/","   "],"118":["   ","   ","\\V7"," V ","   "],"119":["    ","    ","\\VV7"," VV ","    "],"120":["   ","   ","\\V7","/n\\","   "],"121":["    ","__  ","\\ V7"," )/ ","//  "],"122":["     "," __  ","|_ / "," /__|","     "],"123":["  _"," //","/|$","\\|$"," \\\\"],"124":[" _ ","| |","| |","| |","|_|"],"125":["_  ","\\\\ ","$|\\","$|/","// "],"126":[" _  ","//V7","  $ ","  $ ","    "],"160":["$","$","$","$","$"],"161":["()","  ","||","||","L|"],"165":["__ __","\\_V_/","[___]"," |_| ","     "],"166":["||","L|","  ","||","L|"],"168":["    ","()()"," $$ "," $$ ","    "],"183":[" _ ","(_)"," $ "," $ ","   "],"192":["  \\\\ "," / \\ ","| o |","|_n_|","     "],"193":[" //  "," / \\ ","| o |","|_n_|","     "],"194":[" /^\\ "," / \\ ","| o |","|_n_|","     "],"195":[" /\\/ "," / \\ ","| o |","|_n_|","     "],"196":["()_()"," / \\ ","| o |","|_n_|","     "],"197":[" (o) "," / \\ ","| o |","|_n_|","     "],"198":["  ____ "," /  __|","| o _| ","|_n___|","       "],"199":["  __ "," / _|","( (_ "," \\__|","  _) "],"200":[" \\\\_ ","| __|","| _| ","|___|","     "],"201":[" //_ ","| __|","| _| ","|___|","     "],"202":[" /^\\ ","| __|","| _| ","|___|","     "],"203":["()_()","| __|","| _| ","|___|","     "],"204":[" \\\\","| |","| |","|_|","   "],"205":[" //","| |","| |","|_|","   "],"206":["/^\\","| |","| |","|_|","   "],"207":["()_()"," | | "," | | "," |_| ","     "],"209":[" _/\\/ ","| \\| |","| \\\\ |","|_|\\_|","      "],"210":["  \\\\ "," / \\ ","( o )"," \\_/ ","     "],"211":[" //  "," / \\ ","( o )"," \\_/ ","     "],"212":[" /^\\ "," / \\ ","( o )"," \\_/ ","     "],"213":[" /\\/ "," / \\ ","( o )"," \\_/ ","     "],"214":["()_()"," / \\ ","( o )"," \\_/ ","     "],"217":[" _\\\\ ","| | |","| U |","|___|","     "],"218":[" //_ ","| | |","| U |","|___|","     "],"219":[" /^\\ ","| | |","| U |","|___|","     "],"220":["()_()","| | |","| U |","|___|","     "],"223":[" __ ","|o )","|o \\","||_/","L|  "],"224":[" _  "," `` ","/o\\ ","\\_,]","    "],"225":["  _ "," '' ","/o\\ ","\\_,]","    "],"226":["    "," ^  ","/o\\ ","\\_,]","    "],"227":["    "," ~  ","/o\\ ","\\_,]","    "],"228":["    ","O_O ","/o\\ ","\\_,]","    "],"229":["    "," O  ","/o\\ ","\\_,]","    "],"230":["     "," _ _ ","/oYo\\","\\_,( ","     "],"231":["  "," _","//","\\\\"," Z"],"232":[" _ "," ``","/o\\","\\( ","   "],"233":["  _"," ''","/o\\","\\( ","   "],"234":["   "," ^ ","/o\\","\\( ","   "],"235":["   ","O_O","/o\\","\\( ","   "],"236":["_ ","``","||","L|","  "],"237":[" _","''","||","L|","  "],"238":["  ","'`","||","L|","  "],"239":["  ","OO","||","L|","  "],"241":["    ","  ~ ","|/ \\","L_n|","    "],"242":[" _ "," ``","/o\\","\\_/","   "],"243":["  _"," ''","/o\\","\\_/","   "],"244":["   "," ^ ","/o\\","\\_/","   "],"245":["   "," ~ ","/o\\","\\_/","   "],"246":["   ","O_O","/o\\","\\_/","   "],"249":[" _ "," ``","|U|","\\_/","   "],"250":["  _"," ''","|U|","\\_/","   "],"251":["   "," ^ ","|U|","\\_/","   "],"252":["   ","O O","|U|","\\_/","   "],"253":["  _ ","_'' ","\\ V7"," )/ ","//  "],"255":["    ","_O O","\\ V7"," )/ ","//  "],"options":{"hardBlank":"$","height":5,"baseline":4,"maxLength":10,"oldLayout":62,"numCommentLines":8,"printDirection":null,"fullLayout":null,"codeTagCount":null,"fittingRules":{"vRule5":false,"vRule4":false,"vRule3":false,"vRule2":false,"vRule1":false,"hRule6":true,"hRule5":true,"hRule4":true,"hRule3":true,"hRule2":true,"hRule1":false,"hLayout":3,"vLayout":0}},"comment":"\nThis font is (c) Michel Eftimakis 1995 -- Version 2.0 -- 27 jan 1995\n ____________________________________________________________   /`____ \n| Michel Eftimakis                  |     \"Ascii-Artist\"     '\\/      |\n|   Michel.Eftimakis@ustc.vlsi.com  |                  Boo)- (00)     ||\n|   Tel : (33) 92 96 27 19          |                       (_`'_)    ||\n|__ Fax : (33) 92 96 27 01 _________|____ FRANCE ___________ _!!_ ____||\n |_____________________________________________________________________|","numChars":163}