{"32":["      ","      ","      ","      ","      ","      ","      ","      ","      "],"33":["   ","/\\ ","\\/ ","}{ ","\\/ ","   ","<> ","   ","   "],"34":["<> <> "," )  ) ","      ","      ","      ","      ","      ","      ","      "],"35":["  <> <>   ","  }{ }{   ","<>++=++<> ","  }{ }{   ","<>++=++<> ","  }{ }{   ","  <> <>   ","          ","          "],"36":[" _++_, ","||||   ","||--.  "," ~|||| ","  |||| ",",-__-  ","  ||   ","       ","       "],"37":["      ","    , ","<>  / ","   /  ","  /   "," /    ","/  <> ","`     ","      "],"38":["      "," /\\   "," \\/   "," /\\ , ","/'\\\\, ","|  \\\\ ","\\\\-/\\ ","      ","      "],"39":["<>"," )","  ","  ","  ","  ","  ","  ","  "],"40":[" / ","// ","|| ","|| ","|| ","\\\\ "," \\ ","   ","   "],"41":["\\  ","\\\\ ","|| ","|| ","|| ","// ","/  ","   ","   "],"42":["        "," <> <>  ","  \\ /   ","<>-*-<> ","  / \\   "," <> <>  ","        ","        ","        "],"43":["       ","       ","  <>   ","  }{   ","<>--<> ","  }{   ","  <>   ","       ","       "],"44":["   ","   ","   ","   ","   ","   ","<> "," ) ","   "],"45":["      ","      ","      ","      ","<>-<> ","      ","      ","      ","      "],"46":["   ","   ","   ","   ","   ","   ","<> ","   ","   "],"47":["      ","    / ","   /  ","  //  ","  /   "," //   "," /    ","/     ","      "],"48":["      "," /\\\\  ","|| || ","|| || ","|| || ","|| || "," \\\\/  ","      ","      "],"49":["     "," /|  ","/||  "," ||  "," ||  "," ||  ",",/-' ","     ","     "],"50":["     "," /\\  ","(  ) ","  // "," //  ","/(   ","{___ ","     ","     "],"51":["____ ","` // "," //  "," \\\\  ","  )) "," //  ","/'   ","     ","     "],"52":["  ,  "," /|  ","/ |  ","__|_ ","---- ","  |  "," ,_, ","     ","     "],"53":["____  ","||  ` ","||_   ","|/ \\  ","   )) ","  //  "," /'   ","      ","      "],"54":["      ","  ,/  "," //   ","((_-  ","|| )) ","(( || "," \\//  ","      ","      "],"55":["____  ","`  || ","   /, ","  //  "," ((   "," ||   "," |'   ","      ","      "],"56":["      "," /\\\\  ","|| || "," \\ /  "," /\\\\  ","// \\\\ ","|| || "," \\\\/  ","      "],"57":["      "," /\\\\  ","|| || ","|| || "," \\/|| ","   || "," \\_/  ","      ","      "],"58":["   ","   ","   ","<> ","   ","   ","<> ","   ","   "],"59":["   ","   ","   ","<> ","   ","   ","<> "," ) ","   "],"60":["      ","    / ","   /  "," //   ","<<    "," \\\\   ","   \\  ","    \\ ","      "],"61":["      ","      ","      ","<>-<> ","      ","<>-<> ","      ","      ","      "],"62":["      ","\\     "," \\    ","  \\\\  ","   >> ","  //  "," /    ","/     ","      "],"63":[" -_  ","/ \\\\ ","` || ","  |, "," ((  ","     "," <>  ","     ","     "],"64":["      "," /\\\\  ","|| || ","||/|| ","||\\|  ","||    "," \\\\_, ","      ","      "],"65":["  ___    "," -   -_, ","(  ~/||  ","(  / ||  "," \\/==||  "," /_ _||  ","(  - \\\\, ","         ","         "],"66":["          ","_-_ _,,   ","   -/  )  ","  ~||_<   ","   || \\\\  ","   ,/--|| ","  _--_-'  "," (        ","          "],"67":["         ","  ,- _~. "," (' /|   ","((  ||   ","((  ||   "," ( / |   ","  -____- ","         ","         "],"68":["          ","-_____    ","  ' | -,  "," /| |  |` "," || |==|| ","~|| |  |, "," ~-____,  ","(         ","          "],"69":["         ","  ,- _~, "," (' /| / ","((  ||/= ","((  ||   "," ( / |   ","  -____- ","         ","         "],"70":["    _ ,","  ,- - "," _||_  ","' ||   ","  ||   ","  |,   ","_-/    ","       ","       "],"71":["    __ ,  ","  ,-| ~   "," ('||/__, ","(( |||  | ","(( |||==| "," ( / |  , ","  -____/  ","          ","          "],"72":["          ","_-_-      ","  /,      ","  || __   "," ~||-  -  ","  ||===|| "," ( \\_, |  ","       `  ","          "],"73":["     ","_-_, ","  // ","  || "," ~|| ","  || ","_-_, ","     ","     "],"74":["       "," _-_,, ","(  //  ","  _||  ","  _||  ","   ||  ","-__-,  ","       ","       "],"75":["          ","_-_-,     ","  // ,    ","  ||/\\\\   "," ~|| <    ","  ||/\\\\   "," _-__,\\\\, ","          ","          "],"76":["        ","_-_-    "," /,     "," ||     ","~||     "," ||     ","(  -__, ","        ","        "],"77":["           ","  /\\\\,/\\\\, "," /| || ||  "," || || ||  "," ||=|= ||  ","~|| || ||  "," |, \\\\,\\\\, ","_-         ","           "],"78":["    __   ","   /  -, ","  ||   ) "," ~||---) "," ~||---, "," ~||  /  ","  |, /   ","-_-  --~ ","         "],"79":["    __     ","  ,-||-,   "," ('|||  )  ","(( |||--)) ","(( |||--)) "," ( / |  )  ","  -____-   ","           ","           "],"80":["         ","-__ /\\\\  ","  ||  \\\\ "," /||__|| "," \\||__|| ","  ||  |, ","_-||-_/  ","  ||     ","         "],"81":["    __     ","  ,-||-,   "," ('|||  )  ","(( |||--)) ","(( |||--)) "," ( / |  )  ","  -____-\\\\ ","           ","           "],"82":["         ","-__ /\\   ","  || \\,  "," /|| /   "," \\||/-   ","  ||  \\  ","_---_-|, ","         ","         "],"83":["        ","  -_-/  "," (_ /   ","(_ --_  ","  --_ ) "," _/  )) ","(_-_-   ","        ","        "],"84":[" ___        ","-   ---___- ","   (' ||    ","  ((  ||    "," ((   ||    ","  (( //     ","    -____-  ","            ","            "],"85":[" _ _    _ , ","- - /  - -  ","  ('||  ||  "," (( ||--||  "," (( ||--||  "," (( /   ||  ","   -___-\\\\, ","            ","            "],"86":[" _      ","- - _-  ","  )-  ) ","  )___) "," ~)___) ","  )  )  "," /-_/   ","        ","        "],"87":[" _        ","- - /, /, ","  )/ )/ ) ","  )__)__) "," ~)__)__) ","  )  )  ) "," /-_/-_/  ","          ","          "],"88":[" _        ","- -    /` ","  \\\\  /   ","   \\\\/    ","  ==/\\==  ","   / \\\\   ","\\\\/   \\\\, ","          ","          "],"89":["         ","-_   _   ","  |,- `  "," ~||__)) "," ~||__)) ","  |_ _,  "," -' -    ","( _-_    ","         "],"90":["      ","_-___ ","    / ","   /  "," =/=  "," /    ","/-__- ","      ","      "],"91":["  __ ","||   ","||   ","||   ","||   ","||   ","||   ","||__ ","     "],"92":["      ","\\     "," \\    "," \\\\   ","  \\   ","  \\\\  ","   \\  ","    \\ ","      "],"93":["__   ","  || ","  || ","  || ","  || ","  || ","  || ","__|| ","     "],"94":["  x   "," / \\  ","/   \\ ","      ","      ","      ","      ","      ","      "],"95":["      ","      ","      ","      ","      ","      ","      ","_____ ","      "],"96":["   ","<> ","(  ","   ","   ","   ","   ","   ","   "],"97":["      ","      ","  _   "," < \\, "," /-|| ","(( || "," \\/\\\\ ","      ","      "],"98":["      ",",,    ","||    ","||/|, ","|| || ","|| |' ","\\\\/   ","      ","      "],"99":["     ","     ","     "," _-_ ","||   ","||   ","\\\\,/ ","     ","     "],"100":["      "," |\\   ","  \\\\  "," / \\\\ ","|| || ","|| || "," \\\\/  ","      ","      "],"101":["      ","      ","      "," _-_  ","|| \\\\ ","||/   ","\\\\,/  ","      ","      "],"102":["     ","  /\\ "," ||  ","=||= "," ||  "," ||  "," \\\\, ","     ","     "],"103":["      ","      ","  _   "," / \\\\ ","|| || ","|| || ","\\\\_-| "," /  \\ ","'----`"],"104":["      ",",,    ","||    ","||/\\\\ ","|| || ","|| || ","\\\\ |/ ","  _/  ","      "],"105":["   ","   "," ' ","\\\\ ","|| ","|| ","\\\\ ","   ","   "],"106":["   ","   "," ' ","\\\\ ","|| ","|| ","|| ","|; ","/  "],"107":["     ",",,   ","||   ","||/\\ ","||_< ","|| | ","\\\\,\\ ","     ","     "],"108":["   ",",, ","|| ","|| ","|| ","|| ","\\\\ ","   ","   "],"109":["         ","         ","         ","\\\\/\\\\/\\\\ ","|| || || ","|| || || ","\\\\ \\\\ \\\\ ","         ","         "],"110":["      ","      ","      ","\\\\/\\\\ ","|| || ","|| || ","\\\\ \\\\ ","      ","      "],"111":["      ","      ","      "," /'\\\\ ","|| || ","|| || ","\\\\,/  ","      ","      "],"112":["      ","      ","      ","-_-_  ","|| \\\\ ","|| || ","||-'  ","|/    ","'     "],"113":["      ","      ","      "," /'\\\\ ","|| || ","|| || ","\\\\,|| ","   || ","   '` "],"114":["      ","      ","      ",",._-_ "," ||   "," ||   "," \\\\,  ","      ","      "],"115":["      ","      ","      "," _-_, ","||_.  "," ~ || ",",-_-  ","      ","      "],"116":["     ","  ,  "," ||  ","=||= "," ||  "," ||  "," \\\\, ","     ","     "],"117":["      ","      ","      ","\\\\ \\\\ ","|| || ","|| || ","\\\\/\\\\ ","      ","      "],"118":["     ","     ",";    ","\\\\/\\ ","|| | ","|| | ","\\\\/  ","     ","     "],"119":["       ","       ",";      ","\\\\/\\/\\ ","|| | | ","|| | | ","\\\\/\\\\/ ","       ","       "],"120":["      ","      ",",     ","\\\\ /` "," \\\\   "," /\\\\  ","/  \\; ","      ","      "],"121":["       ","       ","       ","'\\\\/\\\\ "," || ;' "," ||/   "," |/    ","(      "," -_-   "],"122":["    ","    ","    ","/\\\\ "," /  ","/\\\\ "," || "," /  ","(,  "],"123":["   _ ","  (  ","  )  ","  )  ","-{   ","  )  ","  )  ","  (_ ","     "],"124":["   ","|| ","|| ","|| ","|| ","|| ","|| ","|| ","   "],"125":["_    "," )   "," (   "," (   ","  }- "," (   "," (   ","_)   ","     "],"126":[" _    ","/ \\_/ ","      ","      ","      ","      ","      ","      ","      "],"196":["  ___    "," -   -_, ","(  ~/||  ","(  / ||  "," \\/==||  "," /_ _||  ","(  - \\\\, ","         ","         "],"214":["    __     ","  ,-||-,   "," ('|||  )  ","(( |||--)) ","(( |||--)) "," ( / |  )  ","  -____-   ","           ","           "],"220":[" _ _    _ , ","- - /  - -  ","  ('||  ||  "," (( ||--||  "," (( ||--||  "," (( /   ||  ","   -___-\\\\, ","            ","            "],"223":["          ","_-_ _,,   ","   -/  )  ","  ~||_<   ","   || \\\\  ","   ,/--|| ","  _--_-'  "," ( ||     ","   ||     "],"228":["      "," ` `  ","  _   "," < \\, "," /-|| ","(( || "," \\/\\\\ ","      ","      "],"246":["      "," ` `  ","      "," /'\\\\ ","|| || ","|| || ","\\\\,/  ","      ","      "],"252":["      "," ` `  ","      ","\\\\ \\\\ ","|| || ","|| || ","\\\\/\\\\ ","      ","      "],"options":{"hardBlank":"$","height":9,"baseline":8,"maxLength":14,"oldLayout":-1,"numCommentLines":16,"printDirection":null,"fullLayout":null,"codeTagCount":null,"fittingRules":{"vRule5":false,"vRule4":false,"vRule3":false,"vRule2":false,"vRule1":false,"hRule6":false,"hRule5":false,"hRule4":false,"hRule3":false,"hRule2":false,"hRule1":false,"hLayout":0,"vLayout":0}},"comment":"Gothic.flf - Taken from a banner program called \"gothic\" by Howard Chu\nFigletization suggested bu Bob Bright (bright@cc.umanitoba.ca)\nFigletized by Wendell Hicken 11/19/93 (whicken@parasoft.com)\nVersion 1.1 - updated on 11/23/93\nVersion 1.11 - updated on 11/28/93 by Brian Tao (taob@io.org)\n             - adjusted baseline and fixed some spacing problems\nExplanation of first line:\nflf2 - \"magic number\" for file identification\na    - should always be `a', for now\n$    - the \"hardblank\" -- prints as a blank, but can't be smushed\n9    - height of a character\n8    - height of a character, not including descenders\n14   - max line length (excluding comment lines) + a fudge factor\n-1   - default smushmode for this font (like \"-m 15\" on command line)\n16   - number of comment lines\n","numChars":102}